[{"binary_accuracy": 0.6645874977, "step": 0}, {"binary_accuracy": 0.7165125012, "step": 1}, {"binary_accuracy": 0.7410874963, "step": 2}, {"binary_accuracy": 0.7589374781, "step": 3}, {"binary_accuracy": 0.7768499851, "step": 4}, {"binary_accuracy": 0.7917125225, "step": 5}, {"binary_accuracy": 0.8056250215, "step": 6}, {"binary_accuracy": 0.8179500103, "step": 7}, {"binary_accuracy": 0.8283625245, "step": 8}, {"binary_accuracy": 0.8391500115, "step": 9}, {"binary_accuracy": 0.8482624888, "step": 10}, {"binary_accuracy": 0.8585000038, "step": 11}, {"binary_accuracy": 0.8655499816, "step": 12}, {"binary_accuracy": 0.8728625178, "step": 13}, {"binary_accuracy": 0.8800874949, "step": 14}, {"binary_accuracy": 0.8847749829, "step": 15}, {"binary_accuracy": 0.8912624717, "step": 16}, {"binary_accuracy": 0.8961750269, "step": 17}, {"binary_accuracy": 0.9013875127, "step": 18}, {"binary_accuracy": 0.9078999758, "step": 19}, {"binary_accuracy": 0.9106374979, "step": 20}, {"binary_accuracy": 0.9156000018, "step": 21}, {"binary_accuracy": 0.9188625216, "step": 22}, {"binary_accuracy": 0.9233250022, "step": 23}, {"binary_accuracy": 0.925562501, "step": 24}]